{"graph":{"type":"XNode.Examples.MathGraph, Assembly-CSharp, Version=0.0.0.0, Culture=neutral, PublicKeyToken=null","name":"Math","id":10106,"nodes":[-2550,-2552,-2554]},"connections":[],"nodes":[{"name":"Display Value","type":"XNode.Examples.MathNodes.DisplayValue, Assembly-CSharp, Version=0.0.0.0, Culture=neutral, PublicKeyToken=null","position":{"x":-280,"y":-184},"id":-2550,"ports":[{"name":"input","id":-1260219008,"dynamic":false,"valueType":"XNode.Examples.MathNodes.DisplayValue+Anything, Assembly-CSharp, Version=0.0.0.0, Culture=neutral, PublicKeyToken=null","typeConstraint":0,"connectionType":1,"direction":0}],"input":{},"graph":10106},{"name":"Display Value","type":"XNode.Examples.MathNodes.DisplayValue, Assembly-CSharp, Version=0.0.0.0, Culture=neutral, PublicKeyToken=null","position":{"x":-312,"y":-40},"id":-2552,"ports":[{"name":"input","id":-726628608,"dynamic":false,"valueType":"XNode.Examples.MathNodes.DisplayValue+Anything, Assembly-CSharp, Version=0.0.0.0, Culture=neutral, PublicKeyToken=null","typeConstraint":0,"connectionType":1,"direction":0}],"input":{},"graph":10106},{"name":"Math Node","type":"XNode.Examples.MathNodes.MathNode, Assembly-CSharp, Version=0.0.0.0, Culture=neutral, PublicKeyToken=null","position":{"x":-88,"y":-136},"id":-2554,"ports":[{"name":"a","id":-1085271552,"dynamic":false,"valueType":"System.Single, mscorlib, Version=4.0.0.0, Culture=neutral, PublicKeyToken=b77a5c561934e089","typeConstraint":0,"connectionType":0,"direction":0},{"name":"b","id":882890624,"dynamic":false,"valueType":"System.Single, mscorlib, Version=4.0.0.0, Culture=neutral, PublicKeyToken=b77a5c561934e089","typeConstraint":0,"connectionType":0,"direction":0},{"name":"result","id":-1443914496,"dynamic":false,"valueType":"System.Single, mscorlib, Version=4.0.0.0, Culture=neutral, PublicKeyToken=b77a5c561934e089","typeConstraint":0,"connectionType":0,"direction":1}],"a":0,"b":0,"result":0,"videoClip":{},"mathType":{"value__":0},"graph":10106}]}